pdmn/__init__.py
pdmn/glossary.py
pdmn/idply.py
pdmn/interpret.py
pdmn/parsetab.py
pdmn/pdmn.py
pdmn/problogname.py
pdmn/table.py
pdmn/table_operations.py
pdmn-1.0.0.dist-info/METADATA
pdmn-1.0.0.dist-info/WHEEL
pdmn-1.0.0.dist-info/entry_points.txt
pdmn-1.0.0.dist-info/top_level.txt
pdmn-1.0.0.dist-info/RECORD
