Metadata-Version: 2.1
Name: pdmn
Version: 1.0.0
Summary: A package providing a pDMN solver
Home-page: UNKNOWN
Author: Simon Vandevelde
Author-email: s.vandevelde@kuleuven.be
License: UNKNOWN
Platform: UNKNOWN
Requires-Python: >=3.6
Requires-Dist: openpyxl (==3.0.10)
Requires-Dist: ply (==3.11)
Requires-Dist: numpy (==1.24.1)
Requires-Dist: python-dateutil
Requires-Dist: problog (==2.2.4)
